visdom_observer/__init__.py
visdom_observer/visdom_observer.py
visdom_observer-0.2.1.dist-info/DESCRIPTION.rst
visdom_observer-0.2.1.dist-info/METADATA
visdom_observer-0.2.1.dist-info/RECORD
visdom_observer-0.2.1.dist-info/WHEEL
visdom_observer-0.2.1.dist-info/metadata.json
visdom_observer-0.2.1.dist-info/top_level.txt
